crainets/__init__.py
crainets/base/trainer_base.py
crainets/config/logger.py
crainets/essentials/metrics.py
crainets/essentials/multi_loss.py
crainets/essentials/multi_metric.py
crainets/essentials/multi_tracker.py
crainets/losses/SSIMLoss.py
crainets/models/ResXUNet/__init__.py
crainets/models/ResXUNet/resxunet.py
crainets/models/UNet/__init__.py
crainets/models/UNet/unet.py
crainets/models/UNet/unet_blocks.py
crainets/models/__init__.py
crainets/models/blocks/BiFPN/BiFPN.py
crainets/models/blocks/BiFPN/__init__.py
crainets/models/blocks/__init__.py
crainets/models/blocks/basicblock.py
crainets/models/blocks/bottleneck.py
crainets/models/blocks/lstm_cell.py
crainets/models/blocks/mbconvblock.py
crainets/models/blocks/squeeze_excitation.py
crainets/models/blocks/utils/__init__.py
crainets/models/blocks/utils/conv_pad.py
crainets/models/blocks/utils/pool_pad.py
crainets/models/blocks/utils/utils.py
crainets/models/efficientnet/__init__.py
crainets/models/efficientnet/config.py
crainets/models/efficientnet/efficientnet.py
crainets/models/efficientnet/utils.py
crainets/trainer/__init__.py
crainets/trainer/trainer.py
crainets-0.1.1b0.dist-info/LICENSE.md
crainets-0.1.1b0.dist-info/WHEEL
crainets-0.1.1b0.dist-info/METADATA
crainets-0.1.1b0.dist-info/RECORD
